funcmeasure/__init__.py
funcmeasure/funcmeasure.py
funcmeasure/_utils/__init__.py
funcmeasure/_utils/function.py
funcmeasure/_utils/function_measurer.py
funcmeasure/_utils/measurement_set.py
funcmeasure/_utils/renderer.py
funcmeasure/models/__init__.py
funcmeasure/models/function_stats.py
funcmeasure/models/enums/__init__.py
funcmeasure/models/enums/table_format.py
funcmeasure-0.1.2.dist-info/LICENSE
funcmeasure-0.1.2.dist-info/METADATA
funcmeasure-0.1.2.dist-info/WHEEL
funcmeasure-0.1.2.dist-info/top_level.txt
funcmeasure-0.1.2.dist-info/RECORD
