Metadata-Version: 2.1
Name: funcmeasure
Version: 0.1.2
Summary: funcmeasure
Home-page: https://github.com/kkristof200/py_funcmeasure
Author: Kristóf-Attila Kovács
License: UNKNOWN
Platform: UNKNOWN
Classifier: Programming Language :: Python :: 3.4
Classifier: Programming Language :: Python :: 3.5
Classifier: Programming Language :: Python :: 3.6
Classifier: Programming Language :: Python :: 3.7
Classifier: Programming Language :: Python :: 3.8
Classifier: Programming Language :: Python :: 3.9
Classifier: License :: OSI Approved :: MIT License
Classifier: Operating System :: OS Independent
Requires-Python: >=3.4
Requires-Dist: jsoncodable (>=0.1.2)
Requires-Dist: tabulate (>=0.8.9)
